newspaper_parser.py
ditaparser-1.0.0.dist-info/DESCRIPTION.rst
ditaparser-1.0.0.dist-info/METADATA
ditaparser-1.0.0.dist-info/metadata.json
ditaparser-1.0.0.dist-info/RECORD
ditaparser-1.0.0.dist-info/top_level.txt
ditaparser-1.0.0.dist-info/WHEEL
