Metadata-Version: 2.0
Name: ditaparser
Version: 1.0.0
Summary: simple parser for newspaper digitaltimes
Home-page: http://zdosaz.blogspot.kr
Author: David Cho
Author-email: csi00700@gmail.com
License: UNKNOWN
Platform: UNKNOWN
Requires-Dist: beautifulsoup4
